compliant_cdk_lib/__init__.py
compliant_cdk_lib/s3.py
compliant_cdk_lib-0.1.3.dist-info/LICENSE
compliant_cdk_lib-0.1.3.dist-info/METADATA
compliant_cdk_lib-0.1.3.dist-info/WHEEL
compliant_cdk_lib-0.1.3.dist-info/RECORD
