Metadata-Version: 2.1
Name: compliant-cdk-lib
Version: 0.1.3
Summary: 
Author: Keith Lagrange
Author-email: punolagrange@gmail.com
Requires-Python: >=3.12,<4.0
Classifier: Programming Language :: Python :: 3
Classifier: Programming Language :: Python :: 3.12
Requires-Dist: aws-cdk-lib (==2.153)
Requires-Dist: pytest (>=8.3.2,<9.0.0)
